LICENSE.txt
setup.cfg
setup.py
tensorrt_lean/__init__.py
tensorrt_lean/plugin/__init__.py
tensorrt_lean/plugin/_autotune.py
tensorrt_lean/plugin/_export.py
tensorrt_lean/plugin/_lib.py
tensorrt_lean/plugin/_plugin_class.py
tensorrt_lean/plugin/_tensor.py
tensorrt_lean/plugin/_top_level.py
tensorrt_lean/plugin/_utils.py
tensorrt_lean/plugin/_validate.py
tensorrt_lean_cu12.egg-info/PKG-INFO
tensorrt_lean_cu12.egg-info/SOURCES.txt
tensorrt_lean_cu12.egg-info/dependency_links.txt
tensorrt_lean_cu12.egg-info/requires.txt
tensorrt_lean_cu12.egg-info/top_level.txt
tensorrt_lean_cu12.egg-info/zip-safe