Metadata-Version: 2.1
Name: tensorrt_lean_cu12
Version: 10.15.1.29
Summary: A high performance deep learning inference library
Home-page: https://github.com/nvidia/tensorrt
Download-URL: https://developer.nvidia.com/tensorrt
Author: NVIDIA Corporation
License: Proprietary
Keywords: nvidia tensorrt deeplearning inference
Classifier: License :: Other/Proprietary License
Classifier: Intended Audience :: Developers
Classifier: Programming Language :: Python :: 3
Requires-Python: >=3.6
License-File: LICENSE.txt
Requires-Dist: tensorrt_lean_cu12_libs==10.15.1.29
Requires-Dist: tensorrt_lean_cu12_bindings==10.15.1.29
Provides-Extra: numpy
Requires-Dist: numpy; extra == "numpy"
